qoqo_braket/__init__.py
qoqo_braket/backend.py
qoqo_braket/post_processing.py
qoqo_braket/interface/__init__.py
qoqo_braket/interface/ionq_verbatim_interface.py
qoqo_braket/interface/oqc_verbatim_interface.py
qoqo_braket/interface/rigetti_verbatim_interface.py
qoqo_braket-0.1.0.dist-info/LICENSE
qoqo_braket-0.1.0.dist-info/METADATA
qoqo_braket-0.1.0.dist-info/WHEEL
qoqo_braket-0.1.0.dist-info/top_level.txt
qoqo_braket-0.1.0.dist-info/RECORD
