Metadata-Version: 2.1
Name: qoqo-braket
Version: 0.1.0
Author-email: HQS Quantum Simulation GmbH <info@quantumsimulations.de>
Maintainer-email: Kirsten Bark <kirsten.bark@quantumsimulations.de>
License: Apache License
Requires-Python: >=3.7
License-File: LICENSE
Requires-Dist: qoqo (>=1.4)
Requires-Dist: qoqo-qasm (>=0.7.4)
Requires-Dist: amazon-braket-sdk
Provides-Extra: dev
Requires-Dist: flake8 ; extra == 'dev'
Requires-Dist: flake8-bandit ; extra == 'dev'
Requires-Dist: flake8-bugbear ; extra == 'dev'
Requires-Dist: flake8-pyproject ; extra == 'dev'
Requires-Dist: flake8-pydocstyle ; extra == 'dev'
Requires-Dist: darglint ; extra == 'dev'
Requires-Dist: bandit ; extra == 'dev'
Requires-Dist: mypy ; extra == 'dev'
Requires-Dist: black ; extra == 'dev'
Provides-Extra: docs
Requires-Dist: sphinx (>=2.1) ; extra == 'docs'
Requires-Dist: nbsphinx ; extra == 'docs'
Requires-Dist: pygments ; extra == 'docs'
Requires-Dist: recommonmark ; extra == 'docs'
Requires-Dist: myst-parser ; extra == 'docs'
Requires-Dist: sphinx-rtd-theme ; extra == 'docs'
Requires-Dist: tomli ; extra == 'docs'
Provides-Extra: tests
Requires-Dist: pytest-cov ; extra == 'tests'
Requires-Dist: pytest ; extra == 'tests'
